keep2roam/__init__.py
keep2roam/__version__.py
keep2roam/cli.py
keep2roam/convert.py
keep2roam/models.py
keep2roam-1.1.dist-info/entry_points.txt
keep2roam-1.1.dist-info/LICENSE
keep2roam-1.1.dist-info/WHEEL
keep2roam-1.1.dist-info/METADATA
keep2roam-1.1.dist-info/RECORD
