Metadata-Version: 2.1
Name: keep2roam
Version: 1.1
Summary: Convert Google Keep Takeout Files to Roam Daily Notes Pages
Home-page: https://github.com/adithyabsk/keep2roam
License: MIT
Author: Adithya Balaji
Author-email: adithyabsk@gmail.com
Requires-Python: >=3.7,<4.0
Classifier: License :: OSI Approved :: MIT License
Classifier: Programming Language :: Python :: 3
Classifier: Programming Language :: Python :: 3.7
Classifier: Programming Language :: Python :: 3.8
Classifier: Programming Language :: Python :: 3.9
Requires-Dist: click (>=7.1.2,<8.0.0)
Requires-Dist: marshmallow (>=3.9.0,<4.0.0)
Project-URL: Repository, https://github.com/adithyabsk/keep2roam
